odoo/addons/sale_operating_unit_sequence/README.rst
odoo/addons/sale_operating_unit_sequence/__init__.py
odoo/addons/sale_operating_unit_sequence/__manifest__.py
odoo/addons/sale_operating_unit_sequence/hooks.py
odoo/addons/sale_operating_unit_sequence/i18n/sale_operating_unit_sequence.pot
odoo/addons/sale_operating_unit_sequence/models/__init__.py
odoo/addons/sale_operating_unit_sequence/models/operating_unit.py
odoo/addons/sale_operating_unit_sequence/models/sale_order.py
odoo/addons/sale_operating_unit_sequence/readme/CONFIGURE.rst
odoo/addons/sale_operating_unit_sequence/readme/CONTRIBUTORS.rst
odoo/addons/sale_operating_unit_sequence/readme/DESCRIPTION.rst
odoo/addons/sale_operating_unit_sequence/static/description/icon.png
odoo/addons/sale_operating_unit_sequence/static/description/index.html
odoo/addons/sale_operating_unit_sequence/tests/__init__.py
odoo/addons/sale_operating_unit_sequence/tests/test_sale_operating_unit_sequence.py
odoo/addons/sale_operating_unit_sequence/views/operating_unit_view.xml
odoo13_addon_sale_operating_unit_sequence-13.0.1.0.1.dev2.dist-info/METADATA
odoo13_addon_sale_operating_unit_sequence-13.0.1.0.1.dev2.dist-info/WHEEL
odoo13_addon_sale_operating_unit_sequence-13.0.1.0.1.dev2.dist-info/top_level.txt
odoo13_addon_sale_operating_unit_sequence-13.0.1.0.1.dev2.dist-info/RECORD
